[
  {
    "id": 1,
    "name": "Иван Петров",
    "phone": "+79001234567",
    "email": "ivan@example.com",
    "createdAt": "2025-01-15T10:00:00.000Z"
  },
  {
    "id": 2,
    "name": "Мария Сидорова",
    "phone": "+79007654321",
    "email": "maria@example.com",
    "createdAt": "2025-01-16T14:30:00.000Z"
  },
  {
    "id": 1765436879272,
    "name": "Елена",
    "phone": "88005555353",
    "email": "hwefhewo@mail.ru",
    "createdAt": "2025-12-11T07:07:59.272Z",
    "updatedAt": "2025-12-11T07:08:34.519Z"
  },
  {
    "id": 1765437773155,
    "name": "Арина",
    "phone": "+793970052525",
    "email": "sfgrdf@mail.ru",
    "createdAt": "2025-12-11T07:22:53.155Z"
  }
]